Flask_MySQL-1.6.0-py3.12-nspkg.pth
flaskext/mysql.py
Flask_MySQL-1.6.0.dist-info/LICENSE
Flask_MySQL-1.6.0.dist-info/METADATA
Flask_MySQL-1.6.0.dist-info/WHEEL
Flask_MySQL-1.6.0.dist-info/namespace_packages.txt
Flask_MySQL-1.6.0.dist-info/top_level.txt
Flask_MySQL-1.6.0.dist-info/RECORD
